dinohash_onnx/__init__.py
dinohash_onnx/downloader.py
dinohash_onnx/hash.py
dinohash_onnx/inference.py
dinohash_onnx/model.py
dinohash_onnx-0.1.0.dist-info/WHEEL
dinohash_onnx-0.1.0.dist-info/METADATA
dinohash_onnx-0.1.0.dist-info/RECORD
